{
   "buffs":
   [
      {
         "id" : "flag_hpbelow_CRIT_buff",
         "stat_type" : "combat_stat_add",
         "stat_sub_type" : "crit_chance",
         "amount" : 0.07,
         "remove_if_not_active" : true,
         "rule_type" : "hpbelow",
         "is_false_rule" : false,
         "rule_data" : {
            "float" : 0.4,
            "string" : ""
         }
      },
      {
         "id" : "flag_hpbelow_DMGL_buff",
         "stat_type" : "combat_stat_multiply",
         "stat_sub_type" : "damage_low",
         "amount" : 0.2,
         "remove_if_not_active" : true,
         "rule_type" : "hpbelow",
         "is_false_rule" : false,
         "rule_data" : {
            "float" : 0.4,
            "string" : ""
         }
      },
      {
         "id" : "flag_hpbelow_DMGH_buff",
         "stat_type" : "combat_stat_multiply",
         "stat_sub_type" : "damage_high",
         "amount" : 0.2,
         "remove_if_not_active" : true,
         "rule_type" : "hpbelow",
         "is_false_rule" : false,
         "rule_data" : {
            "float" : 0.4,
            "string" : ""
         }
      },
      {
         "id" : "flag_grit_prot_1",
         "stat_type" : "combat_stat_add",
         "stat_sub_type" : "protection_rating",
         "amount" : 0.12,
         "remove_if_not_active" : false,
         "rule_type" : "always",
         "is_false_rule" : false,
         "rule_data" : {
            "float" : 0,
            "string" : ""
         }
      },
      {
         "id" : "flag_grit_prot_2",
         "stat_type" : "combat_stat_add",
         "stat_sub_type" : "protection_rating",
         "amount" : 0.15,
         "remove_if_not_active" : false,
         "rule_type" : "always",
         "is_false_rule" : false,
         "rule_data" : {
            "float" : 0,
            "string" : ""
         }
      },
      {
         "id" : "flag_grit_prot_3",
         "stat_type" : "combat_stat_add",
         "stat_sub_type" : "protection_rating",
         "amount" : 0.17,
         "remove_if_not_active" : false,
         "rule_type" : "always",
         "is_false_rule" : false,
         "rule_data" : {
            "float" : 0,
            "string" : ""
         }
      },
      {
         "id" : "flag_grit_prot_4",
         "stat_type" : "combat_stat_add",
         "stat_sub_type" : "protection_rating",
         "amount" : 0.2,
         "remove_if_not_active" : false,
         "rule_type" : "always",
         "is_false_rule" : false,
         "rule_data" : {
            "float" : 0,
            "string" : ""
         }
      },
      {
         "id" : "flag_grit_prot_5",
         "stat_type" : "combat_stat_add",
         "stat_sub_type" : "protection_rating",
         "amount" : 0.24,
         "remove_if_not_active" : false,
         "rule_type" : "always",
         "is_false_rule" : false,
         "rule_data" : {
            "float" : 0,
            "string" : ""
         }
      },
      {
         "id" : "flag_grit_stress_1",
         "stat_type" : "stress_dmg_received_percent",
         "stat_sub_type" : "",
         "amount" : -0.2,
         "remove_if_not_active" : false,
         "rule_type" : "always",
         "is_false_rule" : false,
         "rule_data" : {
            "float" : 0,
            "string" : ""
         }
      },
      {
         "id" : "flag_grit_stress_2",
         "stat_type" : "stress_dmg_received_percent",
         "stat_sub_type" : "",
         "amount" : -0.25,
         "remove_if_not_active" : false,
         "rule_type" : "always",
         "is_false_rule" : false,
         "rule_data" : {
            "float" : 0,
            "string" : ""
         }
      },
      {
         "id" : "flag_grit_stress_3",
         "stat_type" : "stress_dmg_received_percent",
         "stat_sub_type" : "",
         "amount" : -0.3,
         "remove_if_not_active" : false,
         "rule_type" : "always",
         "is_false_rule" : false,
         "rule_data" : {
            "float" : 0,
            "string" : ""
         }
      },
      {
         "id" : "flag_grit_stress_4",
         "stat_type" : "stress_dmg_received_percent",
         "stat_sub_type" : "",
         "amount" : -0.35,
         "remove_if_not_active" : false,
         "rule_type" : "always",
         "is_false_rule" : false,
         "rule_data" : {
            "float" : 0,
            "string" : ""
         }
      },
      {
         "id" : "flag_grit_stress_5",
         "stat_type" : "stress_dmg_received_percent",
         "stat_sub_type" : "",
         "amount" : -0.4,
         "remove_if_not_active" : false,
         "rule_type" : "always",
         "is_false_rule" : false,
         "rule_data" : {
            "float" : 0,
            "string" : ""
         }
      },
      {
         "id" : "flag_grit_deathblow_buff_1",
         "stat_type" : "resistance",
         "stat_sub_type" : "death_blow",
         "amount" : 0.06,
         "remove_if_not_active" : false,
         "rule_type" : "always",
         "is_false_rule" : false,
         "rule_data" : {
            "float" : 0,
            "string" : ""
         }
      },
      {
         "id" : "flag_grit_deathblow_buff_2",
         "stat_type" : "resistance",
         "stat_sub_type" : "death_blow",
         "amount" : 0.07,
         "remove_if_not_active" : false,
         "rule_type" : "always",
         "is_false_rule" : false,
         "rule_data" : {
            "float" : 0,
            "string" : ""
         }
      },
      {
         "id" : "flag_grit_deathblow_buff_3",
         "stat_type" : "resistance",
         "stat_sub_type" : "death_blow",
         "amount" : 0.08,
         "remove_if_not_active" : false,
         "rule_type" : "always",
         "is_false_rule" : false,
         "rule_data" : {
            "float" : 0,
            "string" : ""
         }
      },
      {
         "id" : "flag_grit_deathblow_buff_4",
         "stat_type" : "resistance",
         "stat_sub_type" : "death_blow",
         "amount" : 0.09,
         "remove_if_not_active" : false,
         "rule_type" : "always",
         "is_false_rule" : false,
         "rule_data" : {
            "float" : 0,
            "string" : ""
         }
      },
      {
         "id" : "flag_grit_deathblow_buff_5",
         "stat_type" : "resistance",
         "stat_sub_type" : "death_blow",
         "amount" : 0.1,
         "remove_if_not_active" : false,
         "rule_type" : "always",
         "is_false_rule" : false,
         "rule_data" : {
            "float" : 0,
            "string" : ""
         }
      },
      {
         "id" : "flag_endure_spd_buff_1",
         "stat_type" : "combat_stat_add",
         "stat_sub_type" : "speed_rating",
         "amount" : 2,
         "remove_if_not_active" : false,
         "rule_type" : "always",
         "is_false_rule" : false,
         "rule_data" : {
            "float" : 0,
            "string" : ""
         }
      },
      {
         "id" : "flag_endure_spd_buff_2",
         "stat_type" : "combat_stat_add",
         "stat_sub_type" : "speed_rating",
         "amount" : 2,
         "remove_if_not_active" : false,
         "rule_type" : "always",
         "is_false_rule" : false,
         "rule_data" : {
            "float" : 0,
            "string" : ""
         }
      },
      {
         "id" : "flag_endure_spd_buff_3",
         "stat_type" : "combat_stat_add",
         "stat_sub_type" : "speed_rating",
         "amount" : 3,
         "remove_if_not_active" : false,
         "rule_type" : "always",
         "is_false_rule" : false,
         "rule_data" : {
            "float" : 0,
            "string" : ""
         }
      },
      {
         "id" : "flag_endure_spd_buff_4",
         "stat_type" : "combat_stat_add",
         "stat_sub_type" : "speed_rating",
         "amount" : 3,
         "remove_if_not_active" : false,
         "rule_type" : "always",
         "is_false_rule" : false,
         "rule_data" : {
            "float" : 0,
            "string" : ""
         }
      },
      {
         "id" : "flag_endure_spd_buff_5",
         "stat_type" : "combat_stat_add",
         "stat_sub_type" : "speed_rating",
         "amount" : 4,
         "remove_if_not_active" : false,
         "rule_type" : "always",
         "is_false_rule" : false,
         "rule_data" : {
            "float" : 0,
            "string" : ""
         }
      },
      {
         "id" : "flag_exhaust_heal_done_debuff",
         "stat_type" : "hp_heal_percent",
         "stat_sub_type" : "",
         "amount" : -0.25,
         "remove_if_not_active" : false,
         "rule_type" : "always",
         "is_false_rule" : false,
         "rule_data" : {
            "float" : 0,
            "string" : ""
         },
         "is_clear_debuff_valid": false
      },
      {
         "id" : "flag_exhaust_heal_recvd_debuff",
         "stat_type" : "hp_heal_received_percent",
         "stat_sub_type" : "",
         "amount" : -0.25,
         "remove_if_not_active" : false,
         "rule_type" : "always",
         "is_false_rule" : false,
         "rule_data" : {
            "float" : 0,
            "string" : ""
         },
         "is_clear_debuff_valid": false
      },
      {
         "id" : "flag_exhaust_spd_debuff",
         "stat_type" : "combat_stat_add",
         "stat_sub_type" : "speed_rating",
         "amount" : -3,
         "remove_if_not_active" : false,
         "rule_type" : "always",
         "is_false_rule" : false,
         "rule_data" : {
            "float" : 0,
            "string" : ""
         },
         "is_clear_debuff_valid": false
      },
      {
         "id" : "FdeathsdoorACCbuff",
         "stat_type" : "combat_stat_add",
         "stat_sub_type" : "attack_rating",
         "amount" : 0.05,
         "remove_if_not_active" : true,
         "rule_type" : "always",
         "is_false_rule" : false,
         "rule_data" : {
            "float" : 0,
            "string" : ""
         }
      },
      {
         "id" : "FdeathsdoorDMGLowBuff",
         "stat_type" : "combat_stat_multiply",
         "stat_sub_type" : "damage_low",
         "amount" : 0.2,
         "remove_if_not_active" : true,
         "rule_type" : "always",
         "is_false_rule" : false,
         "rule_data" : {
            "float" : 0,
            "string" : ""
         }
      },
      {
         "id" : "FdeathsdoorDMGHighBuff",
         "stat_type" : "combat_stat_multiply",
         "stat_sub_type" : "damage_high",
         "amount" : 0.2,
         "remove_if_not_active" : true,
         "rule_type" : "always",
         "is_false_rule" : false,
         "rule_data" : {
            "float" : 0,
            "string" : ""
         }
      },
      {
         "id" : "FdeathsdoorSPDBuff",
         "stat_type" : "combat_stat_add",
         "stat_sub_type" : "speed_rating",
         "amount" : 2,
         "remove_if_not_active" : true,
         "rule_type" : "always",
         "is_false_rule" : false,
         "rule_data" : {
            "float" : 0,
            "string" : ""
         }
      },
      {
         "id" : "FdeathsdoorSTUNRESISTBuff",
         "stat_type" : "resistance",
         "stat_sub_type" : "stun",
         "amount" : 0.2,
         "remove_if_not_active" : true,
         "rule_type" : "always",
         "is_false_rule" : false,
         "rule_data" : {
            "float" : 0,
            "string" : ""
         }
      },
      {
         "id" : "FdeathsdoorBLIGHTRESISTBuff",
         "stat_type" : "resistance",
         "stat_sub_type" : "poison",
         "amount" : 0.2,
         "remove_if_not_active" : true,
         "rule_type" : "always",
         "is_false_rule" : false,
         "rule_data" : {
            "float" : 0,
            "string" : ""
         }
      },
      {
         "id" : "FdeathsdoorBLEEDRESISTBuff",
         "stat_type" : "resistance",
         "stat_sub_type" : "bleed",
         "amount" : 0.2,
         "remove_if_not_active" : true,
         "rule_type" : "always",
         "is_false_rule" : false,
         "rule_data" : {
            "float" : 0,
            "string" : ""
         }
      },
      {
         "id" : "FdeathsdoorDEBUFFRESISTBuff",
         "stat_type" : "resistance",
         "stat_sub_type" : "debuff",
         "amount" : 0.2,
         "remove_if_not_active" : true,
         "rule_type" : "always",
         "is_false_rule" : false,
         "rule_data" : {
            "float" : 0,
            "string" : ""
         }
      },
      {
         "id" : "TRINKET_FLAG_DEATHRESIST_B",
         "stat_type" : "resistance",
         "stat_sub_type" : "death_blow",
         "amount" : 0.1,
         "remove_if_not_active" : false,
         "rule_type" : "always",
         "is_false_rule" : false,
         "rule_data" : {
            "float" : 0,
            "string" : ""
         }
      },
      {
         "id" : "TRINKET_FLAG_BLEEDRESIST_LOWHP_B",
         "stat_type" : "resistance",
         "stat_sub_type" : "bleed",
         "amount" : 0.2,
         "remove_if_not_active" : false,
         "rule_type" : "hpbelow",
         "is_false_rule" : false,
         "rule_data" : {
            "float" : 0.4,
            "string" : ""
         }
      },
      {
         "id" : "TRINKET_FLAG_BLIGHTRESIST_LOWHP_B",
         "stat_type" : "resistance",
         "stat_sub_type" : "poison",
         "amount" : 0.2,
         "remove_if_not_active" : false,
         "rule_type" : "hpbelow",
         "is_false_rule" : false,
         "rule_data" : {
            "float" : 0.4,
            "string" : ""
         }
      },
      {
         "id" : "TRINKET_FLAG_BLEEDCHANCE_B",
         "stat_type" : "bleed_chance",
         "stat_sub_type" : "",
         "amount" : 0.2,
         "remove_if_not_active" : false,
         "rule_type" : "always",
         "is_false_rule" : false,
         "rule_data" : {
            "float" : 0,
            "string" : ""
         }
      },
      {
         "id" : "TRINKET_FLAG_HEALDONE_D",
         "stat_type" : "hp_heal_percent",
         "stat_sub_type" : "",
         "amount" : -0.2,
         "remove_if_not_active" : false,
         "rule_type" : "always",
         "is_false_rule" : false,
         "rule_data" : {
            "float" : 0,
            "string" : ""
         }
      },
      {
         "id" : "TRINKET_FLAG_HEALDONE_B",
         "stat_type" : "hp_heal_percent",
         "stat_sub_type" : "",
         "amount" : 0.33,
         "remove_if_not_active" : false,
         "rule_type" : "always",
         "is_false_rule" : false,
         "rule_data" : {
            "float" : 0,
            "string" : ""
         }
      },
      {
         "id" : "TRINKET_FLAG_BLEEDCHANCE_D",
         "stat_type" : "bleed_chance",
         "stat_sub_type" : "",
         "amount" : -0.15,
         "remove_if_not_active" : false,
         "rule_type" : "always",
         "is_false_rule" : false,
         "rule_data" : {
            "float" : 0,
            "string" : ""
         }
      },
      {
         "id" : "TRINKET_FLAG_SPEED_LOWHP_B",
         "stat_type" : "combat_stat_add",
         "stat_sub_type" : "speed_rating",
         "amount" : 4,
         "remove_if_not_active" : false,
         "rule_type" : "hpbelow",
         "is_false_rule" : false,
         "rule_data" : {
            "float" : 0.4,
            "string" : ""
         }
      },
      {
         "id" : "TRINKET_FLAG_DEATHDOOR_DODGE",
         "stat_type" : "combat_stat_add",
         "stat_sub_type" : "defense_rating",
         "amount" : 0.2,
         "remove_if_not_active" : false,
         "rule_type" : "at_deaths_door",
         "is_false_rule" : false,
         "rule_data" : {
            "float" : 0,
            "string" : ""
         }
      },
      {
         "id" : "TRINKET_FLAG_DMGL_STRESSED",
         "stat_type" : "combat_stat_multiply",
         "stat_sub_type" : "damage_low",
         "amount" : 0.2,
         "remove_if_not_active" : false,
         "rule_type" : "stress_above",
         "is_false_rule" : false,
         "rule_data" : {
            "float" : 85,
            "string" : ""
         }
      },
      {
         "id" : "TRINKET_FLAG_DMGH_STRESSED",
         "stat_type" : "combat_stat_multiply",
         "stat_sub_type" : "damage_high",
         "amount" : 0.2,
         "remove_if_not_active" : false,
         "rule_type" : "stress_above",
         "is_false_rule" : false,
         "rule_data" : {
            "float" : 85,
            "string" : ""
         }
      },
      {
         "id" : "TRINKET_FLAG_DMGL_HPBELOW",
         "stat_type" : "combat_stat_multiply",
         "stat_sub_type" : "damage_low",
         "amount" : 0.15,
         "remove_if_not_active" : false,
         "rule_type" : "hpbelow",
         "is_false_rule" : false,
         "rule_data" : {
            "float" : 0.4,
            "string" : ""
         }
      },
      {
         "id" : "TRINKET_FLAG_DMGH_HPBELOW",
         "stat_type" : "combat_stat_multiply",
         "stat_sub_type" : "damage_high",
         "amount" : 0.15,
         "remove_if_not_active" : false,
         "rule_type" : "hpbelow",
         "is_false_rule" : false,
         "rule_data" : {
            "float" : 0.4,
            "string" : ""
         }
      }
   ]
}
